{"name": "NBA 2K21", "description": "NBA 2K21 is the latest title in the world-renowned, best-selling NBA 2K series, delivering an industry-leading sports video game experience. With extensive improvements upon its best-in-class graphics and gameplay, competitive and community online features, and deep, varied game modes, NBA 2K21 offers one-of-a-kind immersion into all facets of NBA basketball and culture - where Everything is Game.", "steam": {"steam_game": false, "appid": null}, "developers": ["Visual Concepts"], "publishers": ["2K Games", "2K"], "platforms": ["PC (Microsoft Windows)", "PlayStation 4", "Xbox One", "Nintendo Switch", "PlayStation 5", "Xbox Series X|S", "Google Stadia"], "genres": ["Simulator", "Sport"], "keywords": [], "release_date": "2020-09-03", "currencies": []}